ddos_blocker/__init__.py
ddos_blocker/admin.py
ddos_blocker/middleware.py
ddos_blocker/models.py
ddos_blocker/redis_adapter.py
ddos_blocker-0.0.13.dist-info/METADATA
ddos_blocker-0.0.13.dist-info/WHEEL
ddos_blocker-0.0.13.dist-info/licenses/LICENSE
ddos_blocker-0.0.13.dist-info/RECORD
