Metadata-Version: 2.3
Name: ddos_blocker
Version: 0.0.13
Summary: A small library for repelling DDoS attacks
Author-email: Ulyana Akinfina <ulyana.akinfina22@gmail.com>, Alexander Chaika <manti.by@gmail.com>
Classifier: License :: OSI Approved :: BSD License
Classifier: Operating System :: OS Independent
Classifier: Programming Language :: Python :: 3
Requires-Python: >=3.10.0
Requires-Dist: django<=5.1.1,>=3.2
Requires-Dist: redis<=5.0,>=4.0
